slacg/__init__.py
slacg/gtwg_codegen.py
slacg/kkt_codegen.py
slacg/ldlt_codegen.py
slacg/mat_vec_mult_codegen.py
slacg/internal/common.py
slacg-0.0.11.dist-info/LICENSE
slacg-0.0.11.dist-info/METADATA
slacg-0.0.11.dist-info/WHEEL
slacg-0.0.11.dist-info/top_level.txt
slacg-0.0.11.dist-info/RECORD
