Metadata-Version: 2.2
Name: slacg
Version: 0.0.11
Summary: Sparse Linear Algebra Code Generation
Author-email: Joao Sousa-Pinto <joaospinto@gmail.com>
License: MIT License
Project-URL: Homepage, https://github.com/joaospinto/slacg
Project-URL: Issues, https://github.com/joaospinto/slacg/issues
Classifier: Programming Language :: Python :: 3
Classifier: License :: OSI Approved :: MIT License
Classifier: Operating System :: OS Independent
Requires-Python: >=3.8
License-File: LICENSE
Requires-Dist: numpy
Requires-Dist: scipy
